{
	"Sword": {
		"type":"weapon",
		"rarity":10,
		"success": {
			"default": 20,
			"vampire": 30,
			"elemental": 15,
			"spirit": 20,
			"demon": 10,
			"ogre": 0,
			"ent": 0
		}
	},
	"Axe": {
		"type":"weapon",
		"rarity":3,
		"success": {
			"default": 30,
			"vampire": 5,
			"elemental": 20,
			"spirit": 10,
			"demon": 30,
			"ogre": 2,
			"ent": 40
		}
	},
	"Dagger": {
		"type":"head",
		"rarity":15,
		"success": {
			"default": 10
		}
	},
	"LifePotion": {
		"rarity":1,
		"type":"potion",
		"success": {
			"default": 0
		}
	}
}